Metadata-Version: 2.1
Name: staremaster
Version: 0.0.5
Summary: STARE sidecar creator
Home-page: https://github.com/SpatioTemporal/STAREMaster_py
Author: Niklas Griessbaum
Author-email: griessbaum@ucsb.edu
Project-URL: Bug Tracker, https://github.com/SpatioTemporal/STAREMaster_py/issues
Classifier: Programming Language :: Python :: 3
Classifier: License :: OSI Approved :: MIT License
Classifier: Operating System :: OS Independent
Requires-Python: >=3.7
Requires-Dist: pyhdf (>=0.10.5)
Requires-Dist: numpy (>=1.23.1)
Requires-Dist: netCDF4 (>=1.6.0)
Requires-Dist: xarray (>=2022.6.0)
Requires-Dist: pystare (>=0.8.9)
Requires-Dist: distributed (>=2022.7.1)
Requires-Dist: dask (>=2022.7.1)
Requires-Dist: scipy (>=1.9.0)
Requires-Dist: filelock (>=3.7.1)
